iolocker/__init__.py
iolocker/constants.py
iolocker/core.py
iolocker/exceptions.py
iolocker/handlers.py
iolocker-1.1.0.dist-info/LICENSE
iolocker-1.1.0.dist-info/METADATA
iolocker-1.1.0.dist-info/WHEEL
iolocker-1.1.0.dist-info/top_level.txt
iolocker-1.1.0.dist-info/RECORD
